mmlab_lightning/__init__.py
mmlab_lightning/datasets/__init__.py
mmlab_lightning/datasets/mmlab_dataset_adapter.py
mmlab_lightning/models/__init__.py
mmlab_lightning/models/mmlab_model_adapter.py
mmlab_lightning/tools/__init__.py
mmlab_lightning/tools/config/__init__.py
mmlab_lightning/tools/config/get_mmconfig.py
mmlab_lightning-1.1.0.dist-info/LICENSE
mmlab_lightning-1.1.0.dist-info/METADATA
mmlab_lightning-1.1.0.dist-info/WHEEL
mmlab_lightning-1.1.0.dist-info/entry_points.txt
mmlab_lightning-1.1.0.dist-info/top_level.txt
mmlab_lightning-1.1.0.dist-info/RECORD
