Metadata-Version: 2.1
Name: mmlab-lightning
Version: 1.1.0
Summary: A wrapper for mmlab repos to use in project_template.
Home-page: https://github.com/shenmishajing/mmlab_lightning
Author: shenmishajing
Author-email: shenmishajing@gmail.com
License: MIT License
Project-URL: Code, https://github.com/shenmishajing/mmlab_lightning
Project-URL: Issue tracker, https://github.com/shenmishajing/mmlab_lightning/issues
Platform: all
Classifier: Development Status :: 5 - Production/Stable
Classifier: Intended Audience :: Developers
Classifier: License :: OSI Approved :: MIT License
Classifier: Operating System :: OS Independent
Classifier: Environment :: GPU :: NVIDIA CUDA
Classifier: Programming Language :: Python
Classifier: Programming Language :: Python :: 3
Classifier: Programming Language :: Python :: Implementation :: CPython
Classifier: Programming Language :: Python :: Implementation :: PyPy
Classifier: Topic :: Software Development :: Libraries
Classifier: Topic :: Software Development :: Libraries :: Python Modules
Classifier: Natural Language :: Chinese (Simplified)
Requires-Python: >=3.8
License-File: LICENSE
Requires-Dist: lightning-template
